erdot/__init__.py
erdot/__main__.py
erdot/b.py
erdot/codegen.py
erdot/dTemplate.py
ERDot-2.3.1.dist-info/LICENSE
ERDot-2.3.1.dist-info/METADATA
ERDot-2.3.1.dist-info/WHEEL
ERDot-2.3.1.dist-info/entry_points.txt
ERDot-2.3.1.dist-info/top_level.txt
ERDot-2.3.1.dist-info/RECORD
