Metadata-Version: 2.1
Name: ERDot
Version: 2.3.1
Summary: UNKNOWN
Home-page: https://github.com/ehne/ERDot
Author: ehne
Author-email: ehne@duck.com
License: UNKNOWN
Platform: UNKNOWN
Requires-Python: >=3
Requires-Dist: Click
Provides-Extra: yaml
Requires-Dist: ruamel.yaml ; extra == 'yaml'
